casiopeia/__init__.py
casiopeia/doe.py
casiopeia/inputchecks.py
casiopeia/intro.py
casiopeia/matrices.py
casiopeia/pe.py
casiopeia/sim.py
casiopeia/system.py
casiopeia/discretization/__init__.py
casiopeia/discretization/discretization.py
casiopeia/discretization/nodiscretization.py
casiopeia/discretization/odecollocation.py
casiopeia/discretization/odemultipleshooting.py
casiopeia/interfaces/__init__.py
casiopeia/interfaces/casadi_interface.py
casiopeia-0.2.1.dist-info/LICENCE.md
casiopeia-0.2.1.dist-info/METADATA
casiopeia-0.2.1.dist-info/WHEEL
casiopeia-0.2.1.dist-info/top_level.txt
casiopeia-0.2.1.dist-info/RECORD
