Metadata-Version: 2.1
Name: casiopeia
Version: 0.2.1
Summary: Casadi Interface for Optimum experimental design and Parameter Estimation and Identification Applications
Home-page: http://github.com/adbuerger/casiopeia/
Author: Adrian Buerger
Author-email: adrian.buerger@hs-karlsruhe.de
License: LGPL
Platform: Linux
Requires-Dist: numpy (>=1.8.2)
Requires-Dist: casadi (==3.1.0)
